odoo/addons/project_milestone_status/README.rst
odoo/addons/project_milestone_status/__init__.py
odoo/addons/project_milestone_status/__manifest__.py
odoo/addons/project_milestone_status/i18n/es.po
odoo/addons/project_milestone_status/i18n/it.po
odoo/addons/project_milestone_status/i18n/project_milestone_status.pot
odoo/addons/project_milestone_status/models/__init__.py
odoo/addons/project_milestone_status/models/project.py
odoo/addons/project_milestone_status/models/project_milestone.py
odoo/addons/project_milestone_status/readme/CONTRIBUTORS.md
odoo/addons/project_milestone_status/readme/DESCRIPTION.md
odoo/addons/project_milestone_status/readme/USAGE.md
odoo/addons/project_milestone_status/static/description/icon.png
odoo/addons/project_milestone_status/static/description/icon.svg
odoo/addons/project_milestone_status/static/description/index.html
odoo/addons/project_milestone_status/tests/__init__.py
odoo/addons/project_milestone_status/tests/common.py
odoo/addons/project_milestone_status/tests/test_project_milestone_status.py
odoo/addons/project_milestone_status/tests/test_project_status.py
odoo/addons/project_milestone_status/views/project_milestone_views.xml
odoo/addons/project_milestone_status/views/project_views.xml
odoo_addon_project_milestone_status-18.0.1.0.0.2.dist-info/METADATA
odoo_addon_project_milestone_status-18.0.1.0.0.2.dist-info/WHEEL
odoo_addon_project_milestone_status-18.0.1.0.0.2.dist-info/top_level.txt
odoo_addon_project_milestone_status-18.0.1.0.0.2.dist-info/RECORD
